Metadata-Version: 1.0
Name: probability-dist-calc
Version: 0.1
Summary: probability distributions calculation
Home-page: UNKNOWN
Author: UNKNOWN
Author-email: UNKNOWN
License: UNKNOWN
Platform: UNKNOWN
